artella/__init__.py
artella/plugins/__init__.py
artella/plugins/savetocloud/__init__.py
artella/plugins/savetocloud/__version__.py
artella/plugins/savetocloud/_version.py
artella/plugins/savetocloud/artella-plugin.json
artella/plugins/savetocloud/savetocloud.py
artella/plugins/savetocloud/resources/savetocloud.png
tests/__init__.py
tests/test_plugin.py
artella_plugins_savetocloud-1.0.6.dist-info/METADATA
artella_plugins_savetocloud-1.0.6.dist-info/WHEEL
artella_plugins_savetocloud-1.0.6.dist-info/top_level.txt
artella_plugins_savetocloud-1.0.6.dist-info/RECORD
