Metadata-Version: 2.1
Name: artella-plugins-savetocloud
Version: 1.0.6
Summary: Artella Plugin that allows to upload new file version directly within DCC.
Home-page: https://github.com/artella/artella-plugins-savetocloud
Author: Artella, Inc
Author-email: support@artella.com
License: UNKNOWN
Platform: UNKNOWN
Requires-Dist: artella-plugins-core
Provides-Extra: dev
Requires-Dist: wheel ; extra == 'dev'
Provides-Extra: test
Requires-Dist: pytest ; extra == 'test'
